upup/__init__.py
upup/main.py
upup-2.4.3.dist-info/LICENSE
upup-2.4.3.dist-info/METADATA
upup-2.4.3.dist-info/WHEEL
upup-2.4.3.dist-info/entry_points.txt
upup-2.4.3.dist-info/top_level.txt
upup-2.4.3.dist-info/zip-safe
upup-2.4.3.dist-info/RECORD
