Metadata-Version: 2.1
Name: upup
Version: 2.4.3
Summary: A terminal tool to upload files to servers based on SSH.
Home-page: https://github.com/XoriieInpottn/upup
Author: xi
Author-email: gylv@mail.ustc.edu.cn
License: MIT License 
Platform: any
Classifier: Programming Language :: Python :: 3.6
Classifier: Programming Language :: Python :: 3.7
Classifier: Programming Language :: Python :: 3.8
License-File: LICENSE
Requires-Dist: paramiko
